{
	"source": {
		"arePartialPointsAllowed": false,
		"bloomsObjectiveLevel": "",
		"guidance": "",
		"instructions": "What is the difference between a sprite and a costume?",
		"learningObjectives": "",
		"metadata": {
			"files": [
				"2.2-its-alive/its-alive.sb3"
			],
			"opened": [
				{
					"content": "2.2-its-alive/its-alive.sb3",
					"panelNumber": 0,
					"type": "file"
				}
			],
			"tags": [
				{
					"name": "Assessment Type",
					"value": "Free Text"
				}
			]
		},
		"name": "What is the difference between a sprite and a costume?",
		"oneTimeTest": false,
		"points": 0,
		"previewType": "NONE",
		"rubrics": [],
		"showGuidanceAfterResponseOption": {
			"type": "Never"
		},
		"showName": false
	},
	"taskId": "free-text-3289492379",
	"type": "free-text"
}